framework_translator/__init__.py
framework_translator/api_client.py
framework_translator/cli.py
framework_translator/config.py
framework_translator/framework.py
framework_translator/sdk.py
framework_translator/testsdk.py
framework_translator-1.1.1.dist-info/METADATA
framework_translator-1.1.1.dist-info/WHEEL
framework_translator-1.1.1.dist-info/entry_points.txt
framework_translator-1.1.1.dist-info/RECORD
