Metadata-Version: 2.4
Name: framework_translator
Version: 1.1.1
Summary: A powerful CLI tool and Python SDK for seamlessly translating code between machine learning frameworks (PyTorch, TensorFlow, JAX, Scikit-learn) using advanced AI models. Features authentication, translation history, and both command-line and programmatic interfaces for developers working across different ML ecosystems.
Author-email: Eitan Tuchin <eitantuchin@gmail.com>, Vennela Reddy Singireddy <vennela5@iastate.edu>, Prashanth Kambalapally <kambala@iastate.edu>, Liban Ahmed <lahmed@iastate.edu>, Tirmidi Mohamed <tmohamed@iastate.edu>
License: MIT
Keywords: AI,CLI,LLM,code-generation,code-translation,frameworks,jax,machine-learning,pytorch,scikit-learn,tensorflow
Requires-Dist: cryptography>=42.0.4
Requires-Dist: openai>=1.109.1
Requires-Dist: platformdirs>=4.4.0
Requires-Dist: requests>=2.7.0
Requires-Dist: termcolor>=3.1.0
